memlite/__init__.py
memlite-0.0.0.dist-info/METADATA
memlite-0.0.0.dist-info/WHEEL
memlite-0.0.0.dist-info/top_level.txt
memlite-0.0.0.dist-info/RECORD
